LICENSE
cfddns/__init__.py
cfddns/__main__.py
cfddns/cli.py
cfddns/notification.py
cfddns-1.5.0.dist-info/entry_points.txt
cfddns-1.5.0.dist-info/LICENSE
cfddns-1.5.0.dist-info/WHEEL
cfddns-1.5.0.dist-info/METADATA
cfddns-1.5.0.dist-info/RECORD
